LICENSE
README.md
deciml_maths/__init__.py
deciml_maths/data.py
deciml_maths/functions.py
deciml_maths/matrix.py
deciml_maths/matrix.py.save
deciml_mathematics-0.0.3.dist-info/METADATA
deciml_mathematics-0.0.3.dist-info/WHEEL
deciml_mathematics-0.0.3.dist-info/licenses/LICENSE
deciml_mathematics-0.0.3.dist-info/RECORD
