Metadata-Version: 2.4
Name: deciml_mathematics
Version: 0.0.3
Summary: Implementation of deciml library. Used for mathematical operations.
Project-URL: Homepage, https://github.com/putterPatcher/deciml_mathematics
Project-URL: Issues, https://github.com/putterPatcher/deciml_mathematics/issues
Author-email: Kor Shantanu Nitin <korshantanu@gmail.com>
License: GPL-3.0-only
License-File: LICENSE
Classifier: License :: OSI Approved :: GNU General Public License v3 (GPLv3)
Classifier: Operating System :: OS Independent
Classifier: Programming Language :: Python :: 3
Requires-Python: >=3.8
Requires-Dist: cmpr
Requires-Dist: deciml
Requires-Dist: terminate
